LICENSE
README.md
notion/__init__.py
notion/py.typed
notion/api/__init__.py
notion/api/_about.py
notion/api/_pagination.py
notion/api/_pkgv.py
notion/api/blockmixin.py
notion/api/client.py
notion/api/notionblock.py
notion/api/notiondatabase.py
notion/api/notionpage.py
notion/api/notionworkspace.py
notion/api/block_ext/__init__.py
notion/api/block_ext/code.py
notion/api/block_ext/equation.py
notion/api/block_ext/richtext.py
notion/api/block_ext/table.py
notion/api/block_ext/todo.py
notion/exceptions/__init__.py
notion/exceptions/errors.py
notion/exceptions/validate.py
notion/properties/__init__.py
notion/properties/blocktypes.py
notion/properties/build.py
notion/properties/common.py
notion/properties/files.py
notion/properties/options.py
notion/properties/propertyobjects.py
notion/properties/propertyvalues.py
notion/properties/richtext.py
notion/propertyitems/__init__.py
notion/propertyitems/base.py
notion/propertyitems/call.py
notion/query/__init__.py
notion/query/compound.py
notion/query/conditions.py
notion/query/propfilter.py
notion/query/sort.py
notion/query/timestamp.py
notion_api-0.7.0.dist-info/METADATA
notion_api-0.7.0.dist-info/WHEEL
notion_api-0.7.0.dist-info/licenses/LICENSE
notion_api-0.7.0.dist-info/RECORD
