Metadata-Version: 2.3
Name: notion-api
Version: 0.7.0
Summary: An unofficial wrapper for Notion's API, aiming to simplify the dynamic nature of interacting with Notion.
Project-URL: Homepage, https://github.com/ayvi-0001/notion-api
Project-URL: Source Code, https://github.com/ayvi-0001/notion-api
Author-email: Alan Vickers <alan.k.vickers@gmail.com>
License-File: LICENSE
Keywords: api-wrapper,notion,notion-api
Classifier: Development Status :: 3 - Alpha
Classifier: Intended Audience :: Developers
Classifier: License :: OSI Approved :: MIT License
Classifier: Operating System :: OS Independent
Classifier: Programming Language :: Python :: 3.10
Classifier: Programming Language :: Python :: 3.11
Requires-Python: >=3.10
Requires-Dist: pytz>=2022.7.1
Requires-Dist: requests>=2.28.2
Requires-Dist: tzlocal>=4.2
Provides-Extra: dev
Requires-Dist: black>=23.3.0; extra == 'dev'
Requires-Dist: isort>=5.12.0; extra == 'dev'
Requires-Dist: mypy-extensions>=1.0.0; extra == 'dev'
Requires-Dist: mypy>=1.3.0; extra == 'dev'
Requires-Dist: types-pytz>=2023.3.0.0; extra == 'dev'
Requires-Dist: types-requests>=2.28.11.17; extra == 'dev'
Requires-Dist: types-tzlocal>=4.3.0.0; extra == 'dev'
Requires-Dist: types-urllib3>=1.26.25.10; extra == 'dev'
Requires-Dist: typing-extensions>=4.5.0; extra == 'dev'
